buddybet_transactionmanager/__init__.py
buddybet_transactionmanager/http/__init__.py
buddybet_transactionmanager/http/constants.py
buddybet_transactionmanager/http/exceptions.py
buddybet_transactionmanager/http/transaction_http.py
buddybet_transactionmanager/schemas/__init__.py
buddybet_transactionmanager/schemas/http_response_schema.py
buddybet_transactionmanager-0.5.1.dist-info/METADATA
buddybet_transactionmanager-0.5.1.dist-info/WHEEL
buddybet_transactionmanager-0.5.1.dist-info/RECORD
