Metadata-Version: 2.3
Name: buddybet_transactionmanager
Version: 0.5.1
Summary: Lib for manager Transaction HTTPs
Keywords: http,https,Transaction,request,security
Author: ricardomarzochi07
Author-email: ricardomarzochi@gmail.com
Requires-Python: >=3.12
Classifier: Programming Language :: Python :: 3
Classifier: Programming Language :: Python :: 3.12
Classifier: Programming Language :: Python :: 3.13
Requires-Dist: buddybet-logmon-common (>=0.1.0,<0.2.0)
